{
	"all": [
		{
			"height": 1349,
			"width": 1080,
			"biggie": "https://instagram.fltn3-1.fna.fbcdn.net/v/t51.2885-15/308919608_501744238074759_8513410391929819772_n.jpg?stp=dst-jpg_e35_p1080x1080&_nc_ht=instagram.fltn3-1.fna.fbcdn.net&_nc_cat=103&_nc_ohc=0D9Mrgly26AAX_VqK4B&edm=APU89FABAAAA&ccb=7-5&oh=00_AT9yT07u4lgyZCxmqP8NHCPhuEatyTCUY0V8t0J1dyzJgg&oe=633C221D&_nc_sid=86f79a",
			"thumbnail": "https://instagram.fltn3-1.fna.fbcdn.net/v/t51.2885-15/308919608_501744238074759_8513410391929819772_n.jpg?stp=c0.179.1440.1440a_dst-jpg_e35_s640x640_sh0.08&_nc_ht=instagram.fltn3-1.fna.fbcdn.net&_nc_cat=103&_nc_ohc=0D9Mrgly26AAX_VqK4B&edm=APU89FABAAAA&ccb=7-5&oh=00_AT--nbSeAfZSr9vxvnZplCe0bg0fNUsCcvoq7uW05hNCbg&oe=633C221D&_nc_sid=86f79a",
			"url": "https://instagram.com/p/CjBJrxhKJBN",
			"id": "2936671022548029517"
		},
		{
			"height": 1349,
			"width": 1080,
			"biggie": "https://instagram.fltn3-1.fna.fbcdn.net/v/t51.2885-15/308809863_5641375395916152_3988928228807282747_n.jpg?stp=dst-jpg_e35_p1080x1080&_nc_ht=instagram.fltn3-1.fna.fbcdn.net&_nc_cat=100&_nc_ohc=wvns7XdMtF4AX8hyFN9&edm=APU89FABAAAA&ccb=7-5&oh=00_AT9lbHermzGNkvd707N5oqVg2Ey357XACkT13u6xZ7tdUw&oe=633BE890&_nc_sid=86f79a",
			"thumbnail": "https://instagram.fltn3-1.fna.fbcdn.net/v/t51.2885-15/308809863_5641375395916152_3988928228807282747_n.jpg?stp=c0.179.1440.1440a_dst-jpg_e35_s640x640_sh0.08&_nc_ht=instagram.fltn3-1.fna.fbcdn.net&_nc_cat=100&_nc_ohc=wvns7XdMtF4AX8hyFN9&edm=APU89FABAAAA&ccb=7-5&oh=00_AT_ZuNL6dmUV6nzJ5pz8sEojhYXJyOoHUzc_A4mvCg7ZRg&oe=633BE890&_nc_sid=86f79a",
			"url": "https://instagram.com/p/Ci8CFWwKaSz",
			"id": "2935230221259482291"
		},
		{
			"height": 1349,
			"width": 1080,
			"biggie": "https://instagram.fltn3-1.fna.fbcdn.net/v/t51.2885-15/308281668_837884797235507_2947268734656224829_n.jpg?stp=dst-jpg_e35_p1080x1080&_nc_ht=instagram.fltn3-1.fna.fbcdn.net&_nc_cat=111&_nc_ohc=M3iGO3nbIW4AX-kwaV6&edm=APU89FABAAAA&ccb=7-5&oh=00_AT9sNfNZSMTt122QN4FW3sjh8RsNQTTsYQcQqxMez1d9nw&oe=633AB850&_nc_sid=86f79a",
			"thumbnail": "https://instagram.fltn3-1.fna.fbcdn.net/v/t51.2885-15/308281668_837884797235507_2947268734656224829_n.jpg?stp=c0.179.1440.1440a_dst-jpg_e35_s640x640_sh0.08&_nc_ht=instagram.fltn3-1.fna.fbcdn.net&_nc_cat=111&_nc_ohc=M3iGO3nbIW4AX-kwaV6&edm=APU89FABAAAA&ccb=7-5&oh=00_AT_AWU8nLg20v4XNzv8kG3r3h__dVn2vU3NB4JJuqK0aDQ&oe=633AB850&_nc_sid=86f79a",
			"url": "https://instagram.com/p/Ci2745WKdmI",
			"id": "2933795601888434568"
		},
		{
			"height": 1349,
			"width": 1080,
			"biggie": "https://instagram.fltn3-1.fna.fbcdn.net/v/t51.2885-15/307797659_798297371589317_7595652899546634765_n.jpg?stp=dst-jpg_e35_p1080x1080&_nc_ht=instagram.fltn3-1.fna.fbcdn.net&_nc_cat=105&_nc_ohc=wSLGJJbqc84AX-Mn5B7&edm=APU89FABAAAA&ccb=7-5&oh=00_AT-C0tz3M6XdAikfIaW3zYeeV1wPiD33t6mafdon1tUIxw&oe=633AA51C&_nc_sid=86f79a",
			"thumbnail": "https://instagram.fltn3-1.fna.fbcdn.net/v/t51.2885-15/307797659_798297371589317_7595652899546634765_n.jpg?stp=c0.179.1440.1440a_dst-jpg_e35_s640x640_sh0.08&_nc_ht=instagram.fltn3-1.fna.fbcdn.net&_nc_cat=105&_nc_ohc=wSLGJJbqc84AX-Mn5B7&edm=APU89FABAAAA&ccb=7-5&oh=00_AT__MEtGlaxzSbkU4-JnKWiMrumODYrkplBQEOkHLzkhJg&oe=633AA51C&_nc_sid=86f79a",
			"url": "https://instagram.com/p/Ci0VTV3jiO_",
			"id": "2933062945452467135"
		},
		{
			"height": 1349,
			"width": 1080,
			"biggie": "https://instagram.fltn3-1.fna.fbcdn.net/v/t51.2885-15/307116375_141780318281905_4624892852627987772_n.jpg?stp=dst-jpg_e35_p1080x1080&_nc_ht=instagram.fltn3-1.fna.fbcdn.net&_nc_cat=101&_nc_ohc=Ec8hiw4YlxcAX9ODwhd&edm=APU89FABAAAA&ccb=7-5&oh=00_AT8TKPMDUmZltUnwwlcaEPiZJGcvsa31oPxvE0LT8joAOg&oe=633B297D&_nc_sid=86f79a",
			"thumbnail": "https://instagram.fltn3-1.fna.fbcdn.net/v/t51.2885-15/307116375_141780318281905_4624892852627987772_n.jpg?stp=c0.179.1440.1440a_dst-jpg_e35_s640x640_sh0.08&_nc_ht=instagram.fltn3-1.fna.fbcdn.net&_nc_cat=101&_nc_ohc=Ec8hiw4YlxcAX9ODwhd&edm=APU89FABAAAA&ccb=7-5&oh=00_AT8xdW2mYEYWXrWl776yG_U0RMeULE791UNkhccMlLgIGw&oe=633B297D&_nc_sid=86f79a",
			"url": "https://instagram.com/p/CinmIIPq4xA",
			"id": "2929477767003868224"
		},
		{
			"height": 1349,
			"width": 1080,
			"biggie": "https://instagram.fltn3-1.fna.fbcdn.net/v/t51.2885-15/306799680_1521812854922421_5741525581475865091_n.jpg?stp=dst-jpg_e35_p1080x1080&_nc_ht=instagram.fltn3-1.fna.fbcdn.net&_nc_cat=109&_nc_ohc=LrKYvKLvxaIAX_pqfaK&edm=APU89FABAAAA&ccb=7-5&oh=00_AT9I1rp4CiK4I2XqPeh13pBQXYLfNuIOCB4WqMzR2s1fJg&oe=633C2ABA&_nc_sid=86f79a",
			"thumbnail": "https://instagram.fltn3-1.fna.fbcdn.net/v/t51.2885-15/306799680_1521812854922421_5741525581475865091_n.jpg?stp=c0.179.1440.1440a_dst-jpg_e35_s640x640_sh0.08&_nc_ht=instagram.fltn3-1.fna.fbcdn.net&_nc_cat=109&_nc_ohc=LrKYvKLvxaIAX_pqfaK&edm=APU89FABAAAA&ccb=7-5&oh=00_AT9fGkK2Z_Eb_BfITtOzvkthHFkthE2spbuCIm3HGXIZ-w&oe=633C2ABA&_nc_sid=86f79a",
			"url": "https://instagram.com/p/CiiX6bZqej7",
			"id": "2928007877965244667"
		},
		{
			"height": 1342,
			"width": 1080,
			"biggie": "https://instagram.fltn3-1.fna.fbcdn.net/v/t51.2885-15/305731292_1509843059437740_8415472063670610649_n.jpg?stp=dst-jpg_e35_p1080x1080&_nc_ht=instagram.fltn3-1.fna.fbcdn.net&_nc_cat=100&_nc_ohc=UF7EAsFzP7QAX9BGMvK&edm=APU89FABAAAA&ccb=7-5&oh=00_AT_iJHnxYGNmPJh8RK3jdz7Zd0lOref7XKUp14CZJH-5xg&oe=633AE8D4&_nc_sid=86f79a",
			"thumbnail": "https://instagram.fltn3-1.fna.fbcdn.net/v/t51.2885-15/305731292_1509843059437740_8415472063670610649_n.jpg?stp=c0.175.1440.1440a_dst-jpg_e35_s640x640_sh0.08&_nc_ht=instagram.fltn3-1.fna.fbcdn.net&_nc_cat=100&_nc_ohc=UF7EAsFzP7QAX9BGMvK&edm=APU89FABAAAA&ccb=7-5&oh=00_AT_i5Z3Ug3NitQ05MP48hB8ANQJZPco-99MmPfdmeEjRiw&oe=633AE8D4&_nc_sid=86f79a",
			"url": "https://instagram.com/p/CiRwOFaqSII",
			"id": "2923329707261370888"
		},
		{
			"height": 1350,
			"width": 1080,
			"biggie": "https://instagram.fltn3-1.fna.fbcdn.net/v/t51.2885-15/305339188_5308757622506769_555066925262134091_n.jpg?stp=dst-jpg_e35_p1080x1080&_nc_ht=instagram.fltn3-1.fna.fbcdn.net&_nc_cat=109&_nc_ohc=STz92_Bd57gAX95FJfk&edm=APU89FABAAAA&ccb=7-5&oh=00_AT_lgaX-tJyCZexA5qEzkVroo8yX1dB07rjnGDnWTuoUzQ&oe=633BCBFF&_nc_sid=86f79a",
			"thumbnail": "https://instagram.fltn3-1.fna.fbcdn.net/v/t51.2885-15/305339188_5308757622506769_555066925262134091_n.jpg?stp=c0.180.1440.1440a_dst-jpg_e35_s640x640_sh0.08&_nc_ht=instagram.fltn3-1.fna.fbcdn.net&_nc_cat=109&_nc_ohc=STz92_Bd57gAX95FJfk&edm=APU89FABAAAA&ccb=7-5&oh=00_AT8X3RgMH27znyo9KJD4clanR0TCKaa8MSLFmqNNqMhjdw&oe=633BCBFF&_nc_sid=86f79a",
			"url": "https://instagram.com/p/CiDlfL3qkmZ",
			"id": "2919341854235969945"
		}
	]
}
